mlchain_extension/__init__.py
mlchain_extension/decorator.py
mlchain_extension/cache/__init__.py
mlchain_extension/cache/function.py
mlchain_extension/cache/remote.py
mlchain_extension/cli/__init__.py
mlchain_extension/cli/config.yaml
mlchain_extension/cli/main.py
mlchain_extension/cli/manager.py
mlchain_extension/cli/run.py
mlchain_extension/observe/__init__.py
mlchain_extension/observe/function.py
mlchain_extension/observe/trace_apm.py
mlchain_extension/queue/__init__.py
mlchain_extension/queue/base.py
mlchain_extension/queue/kafka/__init__.py
mlchain_extension/queue/kafka/client.py
mlchain_extension/queue/kafka/server.py
mlchain_extension/queue/redis/__init__.py
mlchain_extension/queue/redis/base.py
mlchain_extension/queue/redis/client.py
mlchain_extension/queue/redis/collect_database.py
mlchain_extension/queue/redis/queue_event.py
mlchain_extension/queue/redis/queue_manager.py
mlchain_extension/queue/redis/server.py
mlchain_extension/queue/redis/swagger.yml
mlchain_extension/storage/__init__.py
mlchain_extension/storage/base.py
mlchain_extension/storage/object_storage.py
mlchain_extension-0.0.4.dist-info/LICENSE.txt
mlchain_extension-0.0.4.dist-info/METADATA
mlchain_extension-0.0.4.dist-info/WHEEL
mlchain_extension-0.0.4.dist-info/entry_points.txt
mlchain_extension-0.0.4.dist-info/top_level.txt
mlchain_extension-0.0.4.dist-info/RECORD
